kb_dashboard_core/__init__.py
kb_dashboard_core/controls/__init__.py
kb_dashboard_core/controls/compile.py
kb_dashboard_core/controls/config.py
kb_dashboard_core/controls/types.py
kb_dashboard_core/controls/view.py
kb_dashboard_core/dashboard/__init__.py
kb_dashboard_core/dashboard/compile.py
kb_dashboard_core/dashboard/config.py
kb_dashboard_core/dashboard/view.py
kb_dashboard_core/dashboard_compiler.py
kb_dashboard_core/filters/__init__.py
kb_dashboard_core/filters/compile.py
kb_dashboard_core/filters/config.py
kb_dashboard_core/filters/view.py
kb_dashboard_core/loader.py
kb_dashboard_core/panels/__init__.py
kb_dashboard_core/panels/auto_layout.py
kb_dashboard_core/panels/base.py
kb_dashboard_core/panels/charts/__init__.py
kb_dashboard_core/panels/charts/base/__init__.py
kb_dashboard_core/panels/charts/base/compile.py
kb_dashboard_core/panels/charts/base/config.py
kb_dashboard_core/panels/charts/base/view.py
kb_dashboard_core/panels/charts/compile.py
kb_dashboard_core/panels/charts/config.py
kb_dashboard_core/panels/charts/datatable/__init__.py
kb_dashboard_core/panels/charts/datatable/compile.py
kb_dashboard_core/panels/charts/datatable/config.py
kb_dashboard_core/panels/charts/datatable/view.py
kb_dashboard_core/panels/charts/esql/columns/__init__.py
kb_dashboard_core/panels/charts/esql/columns/compile.py
kb_dashboard_core/panels/charts/esql/columns/config.py
kb_dashboard_core/panels/charts/esql/columns/view.py
kb_dashboard_core/panels/charts/gauge/__init__.py
kb_dashboard_core/panels/charts/gauge/compile.py
kb_dashboard_core/panels/charts/gauge/config.py
kb_dashboard_core/panels/charts/gauge/view.py
kb_dashboard_core/panels/charts/heatmap/__init__.py
kb_dashboard_core/panels/charts/heatmap/compile.py
kb_dashboard_core/panels/charts/heatmap/config.py
kb_dashboard_core/panels/charts/heatmap/view.py
kb_dashboard_core/panels/charts/lens/__init__.py
kb_dashboard_core/panels/charts/lens/columns/__init__.py
kb_dashboard_core/panels/charts/lens/columns/compile.py
kb_dashboard_core-0.2.7.dist-info/WHEEL
kb_dashboard_core-0.2.7.dist-info/METADATA
kb_dashboard_core-0.2.7.dist-info/RECORD
