Metadata-Version: 2.3
Name: kb-dashboard-core
Version: 0.2.7
Summary: Core compilation engine for YAML to Kibana dashboard format
License: MIT
Classifier: Development Status :: 3 - Alpha
Classifier: Intended Audience :: Developers
Classifier: License :: OSI Approved :: MIT License
Classifier: Programming Language :: Python :: 3
Classifier: Programming Language :: Python :: 3.12
Classifier: Topic :: Software Development :: Code Generators
Requires-Dist: pyyaml>=6.0.3
Requires-Dist: ruamel-yaml>=0.18.0
Requires-Dist: pydantic>=2.12
Requires-Dist: beartype>=0.22
Requires-Dist: humanize>=4.15
Requires-Dist: tatsu>=5.15
Requires-Python: >=3.12
